<?xml version="1.0" encoding="UTF-8" standalone="no"?>
<AudioModification.xml><AudioModification><Name>Lucky_Star</Name><ExternalEvent><Name>Play_Autopilot</Name><Container><Name>Voice</Name><ExternalId>VAutopilot</ExternalId><Path><StateList><State><Name>Autopilot</Name><Value>Checkpoint</Value></State></StateList><FilesList><File><Name>ep01_1319.wem</Name></File><File><Name>ep11_0654.wem</Name></File></FilesList></Path><Path><StateList><State><Name>Autopilot</Name><Value>End</Value></State></StateList><FilesList><File><Name>ep01_0918.wem</Name></File><File><Name>ep06_1143.wem</Name></File></FilesList></Path><Path><StateList><State><Name>Autopilot</Name><Value>Off</Value></State></StateList><FilesList><File><Name>ep01_0308.wem</Name></File></FilesList></Path><Path><StateList><State><Name>Autopilot</Name><Value>On</Value></State></StateList><FilesList><File><Name>OP0001.wem</Name></File></FilesList></Path></Container></ExternalEvent><ExternalEvent><Name>Play_Avatar_Damage</Name><Container><Name>Voice</Name><ExternalId>VAvatar_Damage</ExternalId><Path><StateList><State><Name>Debuff</Name><Value>CriticalFlooding</Value></State></StateList><FilesList><File><Name>ep01_0509.wem</Name></File><File><Name>ep01_0309.wem</Name></File><File><Name>ep06_0350.wem</Name></File></FilesList></Path></Container></ExternalEvent><ExternalEvent><Name>Play_Detection_enemy</Name><Container><Name>Voice</Name><ExternalId>VDetection_enemy</ExternalId><Path><StateList><State><Name>DetectionEnemy</Name><Value>AirCarrier</Value></State></StateList><FilesList><File><Name>ep12_0736.wem</Name></File><File><Name>ep13_1614.wem</Name></File><File><Name>ep16_1454.wem</Name></File><File><Name>ep21_1728.wem</Name></File></FilesList></Path><Path><StateList><State><Name>DetectionEnemy</Name><Value>Battleship</Value></State></StateList><FilesList><File><Name>ep12_0736.wem</Name></File><File><Name>ep13_1614.wem</Name></File><File><Name>ep16_1454.wem</Name></File><File><Name>ep21_1728.wem</Name></File></FilesList></Path><Path><StateList><State><Name>DetectionEnemy</Name><Value>Cruiser</Value></State></StateList><FilesList><File><Name>ep12_0736.wem</Name></File><File><Name>ep13_1614.wem</Name></File><File><Name>ep16_1454.wem</Name></File><File><Name>ep21_1728.wem</Name></File></FilesList></Path><Path><StateList><State><Name>DetectionEnemy</Name><Value>Destroyer</Value></State></StateList><FilesList><File><Name>ep12_0736.wem</Name></File><File><Name>ep13_1614.wem</Name></File><File><Name>ep16_1454.wem</Name></File><File><Name>ep21_1728.wem</Name></File></FilesList></Path><Path><StateList><State><Name>DetectionEnemy</Name><Value>Multi</Value></State></StateList><FilesList><File><Name>ep12_0736.wem</Name></File><File><Name>ep13_1614.wem</Name></File><File><Name>ep16_1454.wem</Name></File><File><Name>ep21_1728.wem</Name></File></FilesList></Path></Container></ExternalEvent><ExternalEvent><Name>Play_DominationStatus</Name><Container><Name>Voice</Name><ExternalId>VDominationStatus</ExternalId><Path><StateList><State><Name>Domination</Name><Value>D_Ally</Value></State></StateList><FilesList><File><Name>ep02_0848.wem</Name></File></FilesList></Path><Path><StateList><State><Name>Domination</Name><Value>D_Enemy</Value></State></StateList><FilesList><File><Name>ep02_0858.wem</Name></File></FilesList></Path><Path><StateList><State><Name>Domination</Name><Value>W_Ally</Value></State></StateList><FilesList><File><Name>ep01_1212.wem</Name></File></FilesList></Path><Path><StateList><State><Name>Domination</Name><Value>W_Enemy</Value></State></StateList><FilesList><File><Name>ep02_0858.wem</Name></File><File><Name>ep17_1036.wem</Name></File></FilesList></Path></Container></ExternalEvent><ExternalEvent><Name>Play_DoubleKill</Name><Container><Name>Voice</Name><ExternalId>VDoubleKill</ExternalId><Path><StateList></StateList><FilesList><File><Name>ep01_1253.rem</Name></File><File><Name>ep02_2150.rem</Name></File></FilesList></Path></Container></ExternalEvent><ExternalEvent><Name>Play_Fire</Name><Container><Name>Voice</Name><ExternalId>VFire</ExternalId><Path><StateList><State><Name>isPlayer</Name><Value>True</Value></State></StateList><FilesList><File><Name>ep01_0833.wem</Name></File><File><Name>ep17_0856.wem</Name></File><File><Name>ep17_1110.wem</Name></File><File><Name>ep19_0634.wem</Name></File><File><Name>ep20_1128.wem</Name></File></FilesList></Path></Container></ExternalEvent><ExternalEvent><Name>Play_FirstKill</Name><Container><Name>Voice</Name><ExternalId>VFirstKill</ExternalId><Path><StateList></StateList><FilesList><File><Name>ep02_0535.wem</Name></File></FilesList></Path></Container></ExternalEvent><ExternalEvent><Name>Play_Frags</Name><Container><Name>Voice</Name><ExternalId>VFrags</ExternalId><Path><StateList><State><Name>Frag_Type</Name><Value>AirCarrier</Value></State><State><Name>isPlayer</Name><Value>False</Value></State></StateList><FilesList><File><Name>ep02_0616.wem</Name></File><File><Name>ep05_0908.wem</Name></File></FilesList></Path><Path><StateList><State><Name>Frag_Type</Name><Value>AirCarrier</Value></State><State><Name>isPlayer</Name><Value>True</Value></State></StateList><FilesList><File><Name>Silence.wem</Name></File></FilesList></Path><Path><StateList><State><Name>Frag_Type</Name><Value>Battleship</Value></State><State><Name>isPlayer</Name><Value>False</Value></State></StateList><FilesList><File><Name>ep02_0616.wem</Name></File><File><Name>ep05_0908.wem</Name></File></FilesList></Path><Path><StateList><State><Name>Frag_Type</Name><Value>Battleship</Value></State><State><Name>isPlayer</Name><Value>True</Value></State></StateList><FilesList><File><Name>Silence.wem</Name></File></FilesList></Path><Path><StateList><State><Name>Frag_Type</Name><Value>Cruiser</Value></State><State><Name>isPlayer</Name><Value>False</Value></State></StateList><FilesList><File><Name>ep02_0616.wem</Name></File><File><Name>ep05_0908.wem</Name></File></FilesList></Path><Path><StateList><State><Name>Frag_Type</Name><Value>Cruiser</Value></State><State><Name>isPlayer</Name><Value>True</Value></State></StateList><FilesList><File><Name>Silence.wem</Name></File></FilesList></Path><Path><StateList><State><Name>Frag_Type</Name><Value>Destroyer</Value></State><State><Name>isPlayer</Name><Value>False</Value></State></StateList><FilesList><File><Name>ep02_0616.wem</Name></File><File><Name>ep05_0908.wem</Name></File></FilesList></Path><Path><StateList><State><Name>Frag_Type</Name><Value>Destroyer</Value></State><State><Name>isPlayer</Name><Value>True</Value></State></StateList><FilesList><File><Name>Silence.wem</Name></File></FilesList></Path></Container></ExternalEvent><ExternalEvent><Name>Play_FriendlyHit</Name><Container><Name>Voice</Name><ExternalId>VFriendlyHit</ExternalId><Path><StateList></StateList><FilesList><File><Name>ep01_1135.wem</Name></File><File><Name>ep01_1417.wem</Name></File><File><Name>ep09_1641.wem</Name></File></FilesList></Path></Container></ExternalEvent><ExternalEvent><Name>Play_GoodHit</Name><Container><Name>Voice</Name><ExternalId>VGoodHit</ExternalId><Path><StateList></StateList><FilesList><File><Name>ep01_0345.wem</Name></File><File><Name>ep01_1710.wem</Name></File><File><Name>ep05_1707.wem</Name></File></FilesList></Path></Container></ExternalEvent><ExternalEvent><Name>Play_Help</Name><Container><Name>Voice</Name><ExternalId>VHelp</ExternalId><Path><StateList><State><Name>HelpType</Name><Value>AirDefenseDisp</Value></State></StateList><FilesList><File><Name>ep02_0739.wem</Name></File></FilesList></Path><Path><StateList><State><Name>HelpType</Name><Value>Engine</Value></State></StateList><FilesList><File><Name>ep01_0144.wem</Name></File><File><Name>ep01_2220.wem</Name></File><File><Name>ep06_0306.wem</Name></File></FilesList></Path><Path><StateList><State><Name>HelpType</Name><Value>Fighter</Value></State></StateList><FilesList><File><Name>ep05_1017.wem</Name></File></FilesList></Path><Path><StateList><State><Name>HelpType</Name><Value>Scout</Value></State></StateList><FilesList><File><Name>ep02_2217.wem</Name></File><File><Name>ep01_2225.wem</Name></File></FilesList></Path><Path><StateList><State><Name>HelpType</Name><Value>Smoke</Value></State></StateList><FilesList><File><Name>ep01_2219.wem</Name></File></FilesList></Path></Container></ExternalEvent><ExternalEvent><Name>Play_Help_End</Name><Container><Name>Voice</Name><ExternalId>VHelp_End</ExternalId><Path><StateList><State><Name>HelpType</Name><Value>AirDefenseDisp</Value></State></StateList><FilesList><File><Name>ep05_1115.wem</Name></File></FilesList></Path><Path><StateList><State><Name>HelpType</Name><Value>CrashCrew</Value></State></StateList><FilesList><File><Name>ep01_1247.wem</Name></File></FilesList></Path><Path><StateList><State><Name>HelpType</Name><Value>Engine</Value></State></StateList><FilesList><File><Name>ep06_0333.wem</Name></File></FilesList></Path><Path><StateList><State><Name>HelpType</Name><Value>Smoke</Value></State></StateList><FilesList><File><Name>ep03_0202.wem</Name></File></FilesList></Path></Container></ExternalEvent><ExternalEvent><Name>Play_Last_Hope</Name><Container><Name>Voice</Name><ExternalId>VLast_Hope</ExternalId><Path><StateList></StateList><FilesList><File><Name>ep18_1425.wem</Name></File><File><Name>ova_2509.wem</Name></File></FilesList></Path></Container></ExternalEvent><ExternalEvent><Name>Play_LetsBatlle</Name><Container><Name>Voice</Name><ExternalId>VLetsBatlle</ExternalId><Path><StateList></StateList><FilesList><File><Name>OP_Talk.wem</Name></File><File><Name>OP_Talk_2.wem</Name></File><File><Name>ep01_1651</Name></File><File><Name>ep01_2159.wem</Name></File><File><Name>ep03_1940.wem</Name></File></FilesList></Path></Container></ExternalEvent><ExternalEvent><Name>Play_Pilots_ID</Name><Container><Name>Voice</Name><ExternalId>VPilots_ID</ExternalId><Path><StateList><State><Name>Plane_Type</Name><Value>Bomber</Value></State><State><Name>PlaneID</Name><Value>id1</Value></State></StateList><FilesList><File><Name>ep15_0639.wem</Name></File></FilesList></Path><Path><StateList><State><Name>Plane_Type</Name><Value>Bomber</Value></State><State><Name>PlaneID</Name><Value>id2</Value></State></StateList><FilesList><File><Name>ep01_2325.wem</Name></File></FilesList></Path><Path><StateList><State><Name>Plane_Type</Name><Value>Bomber</Value></State><State><Name>PlaneID</Name><Value>id3</Value></State></StateList><FilesList><File><Name>ep02_2314.wem</Name></File></FilesList></Path><Path><StateList><State><Name>Plane_Type</Name><Value>Bomber</Value></State><State><Name>PlaneID</Name><Value>id4</Value></State></StateList><FilesList><File><Name>ep03_2327.wem</Name></File></FilesList></Path><Path><StateList><State><Name>Plane_Type</Name><Value>Bomber</Value></State><State><Name>PlaneID</Name><Value>id5</Value></State></StateList><FilesList><File><Name>ep04_2327.wem</Name></File></FilesList></Path><Path><StateList><State><Name>Plane_Type</Name><Value>Bomber</Value></State><State><Name>PlaneID</Name><Value>id6</Value></State></StateList><FilesList><File><Name>ep14_1146.wem</Name></File></FilesList></Path><Path><StateList><State><Name>Plane_Type</Name><Value>Bomber</Value></State><State><Name>PlaneID</Name><Value>id7</Value></State></StateList><FilesList><File><Name>ep14_2314.wem</Name></File></FilesList></Path><Path><StateList><State><Name>Plane_Type</Name><Value>Bomber</Value></State><State><Name>PlaneID</Name><Value>id8</Value></State></StateList><FilesList><File><Name>ep19_2303.wem</Name></File></FilesList></Path><Path><StateList><State><Name>Plane_Type</Name><Value>Bomber</Value></State><State><Name>PlaneID</Name><Value>id9</Value></State></StateList><FilesList><File><Name>ep19_2305.wem</Name></File></FilesList></Path><Path><StateList><State><Name>Plane_Type</Name><Value>Fighter</Value></State><State><Name>PlaneID</Name><Value>id1</Value></State></StateList><FilesList><File><Name>ep15_0639.wem</Name></File></FilesList></Path><Path><StateList><State><Name>Plane_Type</Name><Value>Fighter</Value></State><State><Name>PlaneID</Name><Value>id2</Value></State></StateList><FilesList><File><Name>ep01_2325.wem</Name></File></FilesList></Path><Path><StateList><State><Name>Plane_Type</Name><Value>Fighter</Value></State><State><Name>PlaneID</Name><Value>id3</Value></State></StateList><FilesList><File><Name>ep02_2314.wem</Name></File></FilesList></Path><Path><StateList><State><Name>Plane_Type</Name><Value>Fighter</Value></State><State><Name>PlaneID</Name><Value>id4</Value></State></StateList><FilesList><File><Name>ep03_2327.wem</Name></File></FilesList></Path><Path><StateList><State><Name>Plane_Type</Name><Value>Fighter</Value></State><State><Name>PlaneID</Name><Value>id5</Value></State></StateList><FilesList><File><Name>ep04_2327.wem</Name></File></FilesList></Path><Path><StateList><State><Name>Plane_Type</Name><Value>Fighter</Value></State><State><Name>PlaneID</Name><Value>id6</Value></State></StateList><FilesList><File><Name>ep14_1146.wem</Name></File></FilesList></Path><Path><StateList><State><Name>Plane_Type</Name><Value>Fighter</Value></State><State><Name>PlaneID</Name><Value>id7</Value></State></StateList><FilesList><File><Name>ep14_2314.wem</Name></File></FilesList></Path><Path><StateList><State><Name>Plane_Type</Name><Value>Fighter</Value></State><State><Name>PlaneID</Name><Value>id8</Value></State></StateList><FilesList><File><Name>ep19_2303.wem</Name></File></FilesList></Path><Path><StateList><State><Name>Plane_Type</Name><Value>Fighter</Value></State><State><Name>PlaneID</Name><Value>id9</Value></State></StateList><FilesList><File><Name>ep19_2305.wem</Name></File></FilesList></Path><Path><StateList><State><Name>Plane_Type</Name><Value>Torpedo</Value></State><State><Name>PlaneID</Name><Value>id1</Value></State></StateList><FilesList><File><Name>ep15_0639.wem</Name></File></FilesList></Path><Path><StateList><State><Name>Plane_Type</Name><Value>Torpedo</Value></State><State><Name>PlaneID</Name><Value>id2</Value></State></StateList><FilesList><File><Name>ep01_2325.wem</Name></File></FilesList></Path><Path><StateList><State><Name>Plane_Type</Name><Value>Torpedo</Value></State><State><Name>PlaneID</Name><Value>id3</Value></State></StateList><FilesList><File><Name>ep02_2314.wem</Name></File></FilesList></Path><Path><StateList><State><Name>Plane_Type</Name><Value>Torpedo</Value></State><State><Name>PlaneID</Name><Value>id4</Value></State></StateList><FilesList><File><Name>ep03_2327.wem</Name></File></FilesList></Path><Path><StateList><State><Name>Plane_Type</Name><Value>Torpedo</Value></State><State><Name>PlaneID</Name><Value>id5</Value></State></StateList><FilesList><File><Name>ep04_2327.wem</Name></File></FilesList></Path><Path><StateList><State><Name>Plane_Type</Name><Value>Torpedo</Value></State><State><Name>PlaneID</Name><Value>id6</Value></State></StateList><FilesList><File><Name>ep14_1146.wem</Name></File></FilesList></Path><Path><StateList><State><Name>Plane_Type</Name><Value>Torpedo</Value></State><State><Name>PlaneID</Name><Value>id7</Value></State></StateList><FilesList><File><Name>ep14_2314.wem</Name></File></FilesList></Path><Path><StateList><State><Name>Plane_Type</Name><Value>Torpedo</Value></State><State><Name>PlaneID</Name><Value>id8</Value></State></StateList><FilesList><File><Name>ep19_2303.wem</Name></File></FilesList></Path><Path><StateList><State><Name>Plane_Type</Name><Value>Torpedo</Value></State><State><Name>PlaneID</Name><Value>id9</Value></State></StateList><FilesList><File><Name>ep19_2305.wem</Name></File></FilesList></Path></Container></ExternalEvent><ExternalEvent><Name>Play_Pilots_Status</Name><Container><Name>Voice</Name><ExternalId>VPilots_Status</ExternalId><Path><StateList><State><Name>PlaneStatus</Name><Value>Airborne</Value></State><State><Name>Plane_Type</Name><Value>Bomber</Value></State></StateList><FilesList><File><Name>ep04_0612.wem</Name></File><File><Name>ep05_2158.wem</Name></File></FilesList></Path><Path><StateList><State><Name>PlaneStatus</Name><Value>Airborne</Value></State><State><Name>Plane_Type</Name><Value>Fighter</Value></State></StateList><FilesList><File><Name>ep04_0612.wem</Name></File><File><Name>ep05_2158.wem</Name></File></FilesList></Path><Path><StateList><State><Name>PlaneStatus</Name><Value>Airborne</Value></State><State><Name>Plane_Type</Name><Value>Torpedo</Value></State></StateList><FilesList><File><Name>ep04_0612.wem</Name></File><File><Name>ep05_2158.wem</Name></File></FilesList></Path><Path><StateList><State><Name>PlaneStatus</Name><Value>AtPos</Value></State><State><Name>Plane_Type</Name><Value>Bomber</Value></State></StateList><FilesList><File><Name>ep05_1548.wem</Name></File></FilesList></Path><Path><StateList><State><Name>PlaneStatus</Name><Value>AtPos</Value></State><State><Name>Plane_Type</Name><Value>Fighter</Value></State></StateList><FilesList><File><Name>ep05_1548.wem</Name></File></FilesList></Path><Path><StateList><State><Name>PlaneStatus</Name><Value>AtPos</Value></State><State><Name>Plane_Type</Name><Value>Torpedo</Value></State></StateList><FilesList><File><Name>ep05_1548.wem</Name></File></FilesList></Path><Path><StateList><State><Name>Plane_Type</Name><Value>Bomber</Value></State><State><Name>PlaneStatus</Name><Value>Destroy</Value></State></StateList><FilesList><File><Name>ep02_06421.wem</Name></File><File><Name>ep02_06422.wem</Name></File><File><Name>ep02_06423.wem</Name></File><File><Name>ep02_06424.wem</Name></File><File><Name>ep02_06425.wem</Name></File><File><Name>ep02_06426.wem</Name></File><File><Name>ep05_0724.wem</Name></File><File><Name>ep14_0710.wem</Name></File></FilesList></Path><Path><StateList><State><Name>Plane_Type</Name><Value>Bomber</Value></State><State><Name>PlaneStatus</Name><Value>Engage</Value></State></StateList><FilesList><File><Name>ep02_0850.wem</Name></File><File><Name>ep04_0829.wem</Name></File></FilesList></Path><Path><StateList><State><Name>Plane_Type</Name><Value>Bomber</Value></State><State><Name>PlaneStatus</Name><Value>Land</Value></State></StateList><FilesList><File><Name>ep02_0805wem</Name></File><File><Name>ep06_0645.wem</Name></File></FilesList></Path><Path><StateList><State><Name>Plane_Type</Name><Value>Bomber</Value></State><State><Name>PlaneStatus</Name><Value>Ready</Value></State></StateList><FilesList><File><Name>OP0002.wem</Name></File></FilesList></Path><Path><StateList><State><Name>Plane_Type</Name><Value>Bomber</Value></State><State><Name>PlaneStatus</Name><Value>TangoDown</Value></State></StateList><FilesList><File><Name>ep06_1143.wem</Name></File></FilesList></Path><Path><StateList><State><Name>Plane_Type</Name><Value>Bomber</Value></State><State><Name>PlaneStatus</Name><Value>UnderAttack</Value></State></StateList><FilesList><File><Name>ep05_0736.wem</Name></File><File><Name>ep11_1851.wem</Name></File><File><Name>ep11_1852.wem</Name></File><File><Name>ep11_1853.wem</Name></File><File><Name>ep11_1854.wem</Name></File></FilesList></Path><Path><StateList><State><Name>PlaneStatus</Name><Value>Destroy</Value></State><State><Name>Plane_Type</Name><Value>Fighter</Value></State></StateList><FilesList><File><Name>ep02_06421.wem</Name></File><File><Name>ep02_06422.wem</Name></File><File><Name>ep02_06423.wem</Name></File><File><Name>ep02_06424.wem</Name></File><File><Name>ep02_06425.wem</Name></File><File><Name>ep02_06426.wem</Name></File><File><Name>ep05_0724.wem</Name></File><File><Name>ep14_0710.wem</Name></File></FilesList></Path><Path><StateList><State><Name>PlaneStatus</Name><Value>Destroy</Value></State><State><Name>Plane_Type</Name><Value>FighterCons</Value></State></StateList><FilesList><File><Name>ep02_06421.wem</Name></File><File><Name>ep02_06422.wem</Name></File><File><Name>ep02_06423.wem</Name></File><File><Name>ep02_06424.wem</Name></File><File><Name>ep02_06425.wem</Name></File><File><Name>ep02_06426.wem</Name></File></FilesList></Path><Path><StateList><State><Name>PlaneStatus</Name><Value>Destroy</Value></State><State><Name>Plane_Type</Name><Value>Scout</Value></State></StateList><FilesList><File><Name>ep02_06421.wem</Name></File><File><Name>ep02_06422.wem</Name></File><File><Name>ep02_06423.wem</Name></File><File><Name>ep02_06424.wem</Name></File><File><Name>ep02_06425.wem</Name></File><File><Name>ep02_06426.wem</Name></File></FilesList></Path><Path><StateList><State><Name>PlaneStatus</Name><Value>Destroy</Value></State><State><Name>Plane_Type</Name><Value>Torpedo</Value></State></StateList><FilesList><File><Name>ep02_06421.wem</Name></File><File><Name>ep02_06422.wem</Name></File><File><Name>ep02_06423.wem</Name></File><File><Name>ep02_06424.wem</Name></File><File><Name>ep02_06425.wem</Name></File><File><Name>ep02_06426.wem</Name></File><File><Name>ep05_0724.wem</Name></File><File><Name>ep14_0710.wem</Name></File></FilesList></Path><Path><StateList><State><Name>PlaneStatus</Name><Value>Engage</Value></State><State><Name>Plane_Type</Name><Value>Fighter</Value></State></StateList><FilesList><File><Name>ep02_0850.wem</Name></File><File><Name>ep04_0829.wem</Name></File></FilesList></Path><Path><StateList><State><Name>PlaneStatus</Name><Value>Engage</Value></State><State><Name>Plane_Type</Name><Value>Torpedo</Value></State></StateList><FilesList><File><Name>ep02_0850.wem</Name></File><File><Name>ep04_0829.wem</Name></File></FilesList></Path><Path><StateList><State><Name>Plane_Type</Name><Value>Fighter</Value></State><State><Name>PlaneStatus</Name><Value>Land</Value></State></StateList><FilesList><File><Name>ep02_0805wem</Name></File><File><Name>ep06_0645.wem</Name></File></FilesList></Path><Path><StateList><State><Name>Plane_Type</Name><Value>Fighter</Value></State><State><Name>PlaneStatus</Name><Value>Ready</Value></State></StateList><FilesList><File><Name>OP0002.wem</Name></File></FilesList></Path><Path><StateList><State><Name>Plane_Type</Name><Value>Fighter</Value></State><State><Name>PlaneStatus</Name><Value>TangoDown</Value></State></StateList><FilesList><File><Name>ep06_1143.wem</Name></File></FilesList></Path><Path><StateList><State><Name>Plane_Type</Name><Value>Fighter</Value></State><State><Name>PlaneStatus</Name><Value>UnderAttack</Value></State></StateList><FilesList><File><Name>ep05_0736.wem</Name></File><File><Name>ep11_1851.wem</Name></File><File><Name>ep11_1852.wem</Name></File><File><Name>ep11_1853.wem</Name></File><File><Name>ep11_1854.wem</Name></File></FilesList></Path><Path><StateList><State><Name>Plane_Type</Name><Value>FighterCons</Value></State><State><Name>PlaneStatus</Name><Value>Land</Value></State></StateList><FilesList><File><Name>ep02_0805.wem</Name></File></FilesList></Path><Path><StateList><State><Name>PlaneStatus</Name><Value>Land</Value></State><State><Name>Plane_Type</Name><Value>Scout</Value></State></StateList><FilesList><File><Name>ep02_0805.wem</Name></File></FilesList></Path><Path><StateList><State><Name>PlaneStatus</Name><Value>Land</Value></State><State><Name>Plane_Type</Name><Value>Torpedo</Value></State></StateList><FilesList><File><Name>ep02_0805wem</Name></File><File><Name>ep06_0645.wem</Name></File></FilesList></Path><Path><StateList><State><Name>PlaneStatus</Name><Value>Ready</Value></State><State><Name>Plane_Type</Name><Value>Torpedo</Value></State></StateList><FilesList><File><Name>OP0002.wem</Name></File></FilesList></Path><Path><StateList><State><Name>PlaneStatus</Name><Value>TangoDown</Value></State><State><Name>Plane_Type</Name><Value>Torpedo</Value></State></StateList><FilesList><File><Name>ep06_1143.wem</Name></File></FilesList></Path><Path><StateList><State><Name>Plane_Type</Name><Value>Torpedo</Value></State><State><Name>PlaneStatus</Name><Value>UnderAttack</Value></State></StateList><FilesList><File><Name>ep05_0736.wem</Name></File><File><Name>ep11_1851.wem</Name></File><File><Name>ep11_1852.wem</Name></File><File><Name>ep11_1853.wem</Name></File><File><Name>ep11_1854.wem</Name></File></FilesList></Path></Container></ExternalEvent><ExternalEvent><Name>Play_PriorityTarget</Name><Container><Name>Voice</Name><ExternalId>VPriorityTarget</ExternalId><Path><StateList></StateList><FilesList><File><Name>ep05_0851.wem</Name></File><File><Name>ep05_0903.wem</Name></File><File><Name>ep06_0146.wem</Name></File><File><Name>ep22_1530.wem</Name></File><File><Name>ova_2038.wem</Name></File></FilesList></Path></Container></ExternalEvent><ExternalEvent><Name>Play_quick_commands</Name><Container><Name>Voice</Name><ExternalId>Vquick_commands</ExternalId><Path><StateList><State><Name>quick_commands</Name><Value>CMD_QUICK_AYE_AYE</Value></State></StateList><FilesList><File><Name>ep01_1044.wem</Name></File><File><Name>ep01_1206.wem</Name></File><File><Name>wp02_0325.wem</Name></File></FilesList></Path><Path><StateList><State><Name>quick_commands</Name><Value>CMD_QUICK_CARAMBA</Value></State></StateList><FilesList><File><Name>ep01_1232.wem</Name></File><File><Name>ep01_1545.wem</Name></File><File><Name>ep01_2116.wem</Name></File><File><Name>ep03_0454.wem</Name></File><File><Name>ep08_0247.wem</Name></File></FilesList></Path><Path><StateList><State><Name>quick_commands</Name><Value>CMD_QUICK_GOOD_GAME</Value></State></StateList><FilesList><File><Name>ep02_1453.wem</Name></File><File><Name>ep02_1504.wem</Name></File><File><Name>ep03_1933.wem</Name></File><File><Name>ep09_1417.wem</Name></File></FilesList></Path><Path><StateList><State><Name>quick_commands</Name><Value>CMD_QUICK_GOOD_LUCK</Value></State></StateList><FilesList><File><Name>ep02_0631.wem</Name></File><File><Name>ep07_0146.wem</Name></File></FilesList></Path><Path><StateList><State><Name>quick_commands</Name><Value>CMD_QUICK_NEED_SUPPORT</Value></State></StateList><FilesList><File><Name>ep06_0135.wem</Name></File><File><Name>ep23_1547.wem</Name></File></FilesList></Path><Path><StateList><State><Name>quick_commands</Name><Value>CMD_QUICK_NO_WAY</Value></State></StateList><FilesList><File><Name>ep01_0623.wem</Name></File><File><Name>ep01_1354.wem</Name></File><File><Name>ep02_0838.wem</Name></File><File><Name>ep02_0903.wem</Name></File><File><Name>ep02_1451.wem</Name></File><File><Name>ep03_0443.wem</Name></File><File><Name>ep04_0915.wem</Name></File><File><Name>ep04_1556.wem</Name></File></FilesList></Path><Path><StateList><State><Name>quick_commands</Name><Value>CMD_QUICK_SOS</Value></State></StateList><FilesList><File><Name>ep04_1003.wem</Name></File><File><Name>ep06_0446.wem</Name></File><File><Name>ep08_0146.wem</Name></File><File><Name>ep09_1336.wem</Name></File><File><Name>ep101520.wem</Name></File><File><Name>ep02_2028.wem</Name></File></FilesList></Path><Path><StateList><State><Name>quick_commands</Name><Value>CMD_QUICK_TACTIC_ALLY_BASE</Value></State></StateList><FilesList><File><Name>ep04_0456.wem</Name></File></FilesList></Path><Path><StateList><State><Name>quick_commands</Name><Value>CMD_QUICK_TACTIC_ALLY_POINT</Value></State></StateList><FilesList><File><Name>ep05_1350.wem</Name></File><File><Name>ep05_1450.wem</Name></File><File><Name>ep04_0456.wem</Name></File><File><Name>ep07_0940.wem</Name></File></FilesList></Path><Path><StateList><State><Name>quick_commands</Name><Value>CMD_QUICK_TACTIC_ALLY_SHIP</Value></State></StateList><FilesList><File><Name>ep04_1854.wem</Name></File></FilesList></Path><Path><StateList><State><Name>quick_commands</Name><Value>CMD_QUICK_TACTIC_ENEMY_BASE</Value></State></StateList><FilesList><File><Name>ep05_1350.wem</Name></File><File><Name>ep05_1450.wem</Name></File><File><Name>ep04_0456.wem</Name></File><File><Name>ep07_0940.wem</Name></File></FilesList></Path><Path><StateList><State><Name>quick_commands</Name><Value>CMD_QUICK_TACTIC_ENEMY_POINT</Value></State></StateList><FilesList><File><Name>ep05_1350.wem</Name></File><File><Name>ep05_1450.wem</Name></File><File><Name>ep04_0456.wem</Name></File><File><Name>ep07_0940.wem</Name></File></FilesList></Path><Path><StateList><State><Name>quick_commands</Name><Value>CMD_QUICK_TACTIC_ENEMY_SHIP</Value></State></StateList><FilesList><File><Name>ep05_0851.wem</Name></File><File><Name>ep05_0903.wem</Name></File><File><Name>ep06_0146.wem</Name></File><File><Name>ep22_1530.wem</Name></File><File><Name>ova_2038.wem</Name></File></FilesList></Path><Path><StateList><State><Name>quick_commands</Name><Value>CMD_QUICK_THANK_YOU</Value></State></StateList><FilesList><File><Name>op01_1208.wem</Name></File><File><Name>ep01_1308.wem</Name></File><File><Name>ep02_0902.wem</Name></File><File><Name>ep11_1709.wem</Name></File></FilesList></Path><Path><StateList><State><Name>quick_commands</Name><Value>CMD_QUICK_NEED_AIR_DEFENCE</Value></State></StateList><FilesList><File><Name>Silence.wem</Name></File></FilesList></Path><Path><StateList><State><Name>quick_commands</Name><Value>CMD_QUICK_NEED_SUPPORT_ALLY_PLANE</Value></State></StateList><FilesList><File><Name>Silence.wem</Name></File></FilesList></Path><Path><StateList><State><Name>quick_commands</Name><Value>CMD_QUICK_TACTIC_ENEMY_BUILDING</Value></State></StateList><FilesList><File><Name>Silence.wem</Name></File></FilesList></Path><Path><StateList><State><Name>quick_commands</Name><Value>CMD_QUICK_TACTIC_ALLY_BUILDING</Value></State></StateList><FilesList><File><Name>Silence.wem</Name></File></FilesList></Path><Path><StateList><State><Name>quick_commands</Name><Value>CMD_QUICK_NEED_VISION</Value></State></StateList><FilesList><File><Name>Silence.wem</Name></File></FilesList></Path><Path><StateList><State><Name>quick_commands</Name><Value>CMD_QUICK_BACK_ALLY_SHIP</Value></State></StateList><FilesList><File><Name>ep01_1159.wem</Name></File><File><Name>ep02_0914.wem</Name></File></FilesList></Path><Path><StateList><State><Name>quick_commands</Name><Value>CMD_QUICK_BACK</Value></State></StateList><FilesList><File><Name>ep01_1159.wem</Name></File><File><Name>ep02_0914.wem</Name></File></FilesList></Path><Path><StateList><State><Name>quick_commands</Name><Value>CMD_QUICK_NEED_SMOKE</Value></State></StateList><FilesList><File><Name>ep10_0554.wem</Name></File></FilesList></Path><Path><StateList><State><Name>quick_commands</Name><Value>CMD_QUICK_TACTIC_ALLY_PLANE</Value></State></StateList><FilesList><File><Name>Silence.wem</Name></File></FilesList></Path><Path><StateList><State><Name>quick_commands</Name><Value>CMD_QUICK_TACTIC_ENEMY_PLANE</Value></State></StateList><FilesList><File><Name>Silence.wem</Name></File></FilesList></Path><Path><StateList><State><Name>quick_commands</Name><Value>CMD_QUICK_THANK_YOU_ALLY_SHIP</Value></State></StateList><FilesList><File><Name>op01_1208.wem</Name></File><File><Name>ep01_1308.wem</Name></File><File><Name>ep02_0902.wem</Name></File><File><Name>ep11_1709.wem</Name></File></FilesList></Path><Path><StateList><State><Name>quick_commands</Name><Value>CMD_QUICK_NEED_SUPPORT_ALLY_SHIP</Value></State></StateList><FilesList><File><Name>Silence.wem</Name></File></FilesList></Path><Path><StateList><State><Name>quick_commands</Name><Value>CMD_QUICK_GOOD_GAME_ALLY_SHIP</Value></State></StateList><FilesList><File><Name>ep02_1453.wem</Name></File><File><Name>ep02_1504.wem</Name></File><File><Name>ep03_1933.wem</Name></File><File><Name>ep09_1417.wem</Name></File></FilesList></Path></Container></ExternalEvent><ExternalEvent><Name>Play_quick_commands_receive</Name><Container><Name>Voice</Name><ExternalId>Vquick_commands_receive</ExternalId><Path><StateList><State><Name>quick_commands</Name><Value>CMD_QUICK_AYE_AYE</Value></State></StateList><FilesList><File><Name>ep01_1044.wem</Name></File><File><Name>ep01_1206.wem</Name></File><File><Name>ep02_0325.wem</Name></File></FilesList></Path><Path><StateList><State><Name>quick_commands</Name><Value>CMD_QUICK_CARAMBA</Value></State></StateList><FilesList><File><Name>ep01_1232.wem</Name></File><File><Name>ep01_1545.wem</Name></File><File><Name>ep01_2116.wem</Name></File><File><Name>ep03_0454.wem</Name></File><File><Name>ep08_0247.wem</Name></File></FilesList></Path><Path><StateList><State><Name>quick_commands</Name><Value>CMD_QUICK_GOOD_GAME</Value></State></StateList><FilesList><File><Name>ep02_1453.wem</Name></File><File><Name>ep02_1504.wem</Name></File><File><Name>ep03_1933.wem</Name></File><File><Name>ep09_1417.wem</Name></File></FilesList></Path><Path><StateList><State><Name>quick_commands</Name><Value>CMD_QUICK_GOOD_LUCK</Value></State></StateList><FilesList><File><Name>ep02_0631.wem</Name></File><File><Name>ep07_0146.wem</Name></File></FilesList></Path><Path><StateList><State><Name>quick_commands</Name><Value>CMD_QUICK_NEED_SUPPORT</Value></State></StateList><FilesList><File><Name>ep06_0135.wem</Name></File><File><Name>ep23_1547.wem</Name></File></FilesList></Path><Path><StateList><State><Name>quick_commands</Name><Value>CMD_QUICK_NO_WAY</Value></State></StateList><FilesList><File><Name>ep01_0623.wem</Name></File><File><Name>ep01_1354.wem</Name></File><File><Name>ep02_0838.wem</Name></File><File><Name>ep02_0903.wem</Name></File><File><Name>ep02_1451.wem</Name></File><File><Name>ep03_0443.wem</Name></File><File><Name>ep04_0915.wem</Name></File><File><Name>ep04_1556.wem</Name></File></FilesList></Path><Path><StateList><State><Name>quick_commands</Name><Value>CMD_QUICK_SOS</Value></State></StateList><FilesList><File><Name>ep04_1003.wem</Name></File><File><Name>ep06_0446.wem</Name></File><File><Name>ep08_0146.wem</Name></File><File><Name>ep09_1336.wem</Name></File><File><Name>ep101520.wem</Name></File><File><Name>ep02_2028.wem</Name></File></FilesList></Path><Path><StateList><State><Name>quick_commands</Name><Value>CMD_QUICK_TACTIC_ALLY_BASE</Value></State></StateList><FilesList><File><Name>ep04_0456.wem</Name></File></FilesList></Path><Path><StateList><State><Name>quick_commands</Name><Value>CMD_QUICK_TACTIC_ALLY_POINT</Value></State></StateList><FilesList><File><Name>ep05_1350.wem</Name></File><File><Name>ep05_1450.wem</Name></File><File><Name>ep04_0456.wem</Name></File><File><Name>ep07_0940.wem</Name></File></FilesList></Path><Path><StateList><State><Name>quick_commands</Name><Value>CMD_QUICK_TACTIC_ALLY_SHIP</Value></State></StateList><FilesList><File><Name>ep04_1854.wem</Name></File></FilesList></Path><Path><StateList><State><Name>quick_commands</Name><Value>CMD_QUICK_TACTIC_ENEMY_BASE</Value></State></StateList><FilesList><File><Name>ep05_1350.wem</Name></File><File><Name>ep05_1450.wem</Name></File><File><Name>ep04_0456.wem</Name></File><File><Name>ep07_0940.wem</Name></File></FilesList></Path><Path><StateList><State><Name>quick_commands</Name><Value>CMD_QUICK_TACTIC_ENEMY_POINT</Value></State></StateList><FilesList><File><Name>ep05_1350.wem</Name></File><File><Name>ep05_1450.wem</Name></File><File><Name>ep04_0456.wem</Name></File><File><Name>ep07_0940.wem</Name></File></FilesList></Path><Path><StateList><State><Name>quick_commands</Name><Value>CMD_QUICK_TACTIC_ENEMY_SHIP</Value></State></StateList><FilesList><File><Name>ep05_0851.wem</Name></File><File><Name>ep05_0903.wem</Name></File><File><Name>ep06_0146.wem</Name></File><File><Name>ep22_1530.wem</Name></File><File><Name>ova_2038.wem</Name></File></FilesList></Path><Path><StateList><State><Name>quick_commands</Name><Value>CMD_QUICK_THANK_YOU</Value></State></StateList><FilesList><File><Name>op01_1208.wem</Name></File><File><Name>ep01_1308.wem</Name></File><File><Name>ep02_0902.wem</Name></File><File><Name>ep11_1709.wem</Name></File></FilesList></Path><Path><StateList><State><Name>quick_commands</Name><Value>CMD_QUICK_NEED_AIR_DEFENCE</Value></State></StateList><FilesList><File><Name>Silence.wem</Name></File></FilesList></Path><Path><StateList><State><Name>quick_commands</Name><Value>CMD_QUICK_NEED_SUPPORT_ALLY_PLANE</Value></State></StateList><FilesList><File><Name>Silence.wem</Name></File></FilesList></Path><Path><StateList><State><Name>quick_commands</Name><Value>CMD_QUICK_TACTIC_ENEMY_BUILDING</Value></State></StateList><FilesList><File><Name>Silence.wem</Name></File></FilesList></Path><Path><StateList><State><Name>quick_commands</Name><Value>CMD_QUICK_TACTIC_ALLY_BUILDING</Value></State></StateList><FilesList><File><Name>Silence.wem</Name></File></FilesList></Path><Path><StateList><State><Name>quick_commands</Name><Value>CMD_QUICK_NEED_VISION</Value></State></StateList><FilesList><File><Name>Silence.wem</Name></File></FilesList></Path><Path><StateList><State><Name>quick_commands</Name><Value>CMD_QUICK_BACK_ALLY_SHIP</Value></State></StateList><FilesList><File><Name>ep01_1159.wem</Name></File><File><Name>ep02_0914.wem</Name></File></FilesList></Path><Path><StateList><State><Name>quick_commands</Name><Value>CMD_QUICK_BACK</Value></State></StateList><FilesList><File><Name>ep01_1159.wem</Name></File><File><Name>ep02_0914.wem</Name></File></FilesList></Path><Path><StateList><State><Name>quick_commands</Name><Value>CMD_QUICK_NEED_SMOKE</Value></State></StateList><FilesList><File><Name>Silence.wem</Name></File></FilesList></Path><Path><StateList><State><Name>quick_commands</Name><Value>CMD_QUICK_TACTIC_ALLY_PLANE</Value></State></StateList><FilesList><File><Name>Silence.wem</Name></File></FilesList></Path><Path><StateList><State><Name>quick_commands</Name><Value>CMD_QUICK_TACTIC_ENEMY_PLANE</Value></State></StateList><FilesList><File><Name>Silence.wem</Name></File></FilesList></Path><Path><StateList><State><Name>quick_commands</Name><Value>CMD_QUICK_THANK_YOU_ALLY_SHIP</Value></State></StateList><FilesList><File><Name>op01_1208.wem</Name></File><File><Name>ep01_1308.wem</Name></File><File><Name>ep02_0902.wem</Name></File><File><Name>ep11_1709.wem</Name></File></FilesList></Path><Path><StateList><State><Name>quick_commands</Name><Value>CMD_QUICK_NEED_SUPPORT_ALLY_SHIP</Value></State></StateList><FilesList><File><Name>ep06_0135.wem</Name></File><File><Name>ep23_1547.wem</Name></File></FilesList></Path><Path><StateList><State><Name>quick_commands</Name><Value>CMD_QUICK_GOOD_GAME_ALLY_SHIP</Value></State></StateList><FilesList><File><Name>ep02_1453.wem</Name></File><File><Name>ep02_1504.wem</Name></File><File><Name>ep03_1933.wem</Name></File><File><Name>ep09_1417.wem</Name></File></FilesList></Path></Container></ExternalEvent><ExternalEvent><Name>Play_Task_1</Name><Container><Name>Voice</Name><ExternalId>VTask_1</ExternalId><Path><StateList></StateList><FilesList><File><Name>Seagal_Speech_Tutorial_Task_1.wem</Name></File></FilesList></Path></Container></ExternalEvent><ExternalEvent><Name>Play_Task_2</Name><Container><Name>Voice</Name><ExternalId>VTask_2</ExternalId><Path><StateList></StateList><FilesList><File><Name>Seagal_Speech_Tutorial_Task_2.wem</Name></File></FilesList></Path></Container></ExternalEvent><ExternalEvent><Name>Play_Task_3</Name><Container><Name>Voice</Name><ExternalId>VTask_3</ExternalId><Path><StateList></StateList><FilesList><File><Name>Seagal_Speech_Tutorial_Task_3.wem</Name></File></FilesList></Path></Container></ExternalEvent><ExternalEvent><Name>Play_Task_4</Name><Container><Name>Voice</Name><ExternalId>VTask_4</ExternalId><Path><StateList></StateList><FilesList><File><Name>Seagal_Speech_Tutorial_Task_4.wem</Name></File></FilesList></Path></Container></ExternalEvent><ExternalEvent><Name>Play_Task_5</Name><Container><Name>Voice</Name><ExternalId>VTask_5</ExternalId><Path><StateList></StateList><FilesList><File><Name>Seagal_Speech_Tutorial_Task_5.wem</Name></File></FilesList></Path></Container></ExternalEvent><ExternalEvent><Name>Play_Task_6</Name><Container><Name>Voice</Name><ExternalId>VTask_6</ExternalId><Path><StateList></StateList><FilesList><File><Name>Seagal_Speech_Tutorial_Task_6.wem</Name></File></FilesList></Path></Container></ExternalEvent><ExternalEvent><Name>Play_Task_7</Name><Container><Name>Voice</Name><ExternalId>VTask_7</ExternalId><Path><StateList></StateList><FilesList><File><Name>Seagal_Speech_Tutorial_Task_7.wem</Name></File></FilesList></Path></Container></ExternalEvent><ExternalEvent><Name>Play_Task_8</Name><Container><Name>Voice</Name><ExternalId>VTask_8</ExternalId><Path><StateList></StateList><FilesList><File><Name>Seagal_Speech_Tutorial_Task_8.wem</Name></File></FilesList></Path></Container></ExternalEvent><ExternalEvent><Name>Play_Task_9</Name><Container><Name>Voice</Name><ExternalId>VTask_9</ExternalId><Path><StateList></StateList><FilesList><File><Name>Seagal_Speech_Tutorial_Task_9.1.wem</Name></File></FilesList></Path></Container></ExternalEvent><ExternalEvent><Name>Play_Teamkill_punishment</Name><Container><Name>Voice</Name><ExternalId>VTeamkill_punishment</ExternalId><Path><StateList></StateList><FilesList><File><Name>ep01_1735.wem</Name></File><File><Name>ep01_1559.wem</Name></File></FilesList></Path></Container></ExternalEvent><ExternalEvent><Name>Play_Timer5</Name><Container><Name>Voice</Name><ExternalId>VTimer5</ExternalId><Path><StateList></StateList><FilesList><File><Name>ep11_0422.wem</Name></File></FilesList></Path></Container></ExternalEvent><ExternalEvent><Name>Play_Torpedo_Danger</Name><Container><Name>Voice</Name><ExternalId>VTorpedo_Danger</ExternalId><Path><StateList><State><Name>Torpedo_Location</Name><Value>Torpedo_Ahead</Value></State></StateList><FilesList><File><Name>ep01_1310.wem</Name></File><File><Name>ep06_1035.wem</Name></File><File><Name>ep22_2014.wem</Name></File></FilesList></Path><Path><StateList><State><Name>Torpedo_Location</Name><Value>Torpedo_Back</Value></State></StateList><FilesList><File><Name>ep01_1310.wem</Name></File><File><Name>ep06_1035.wem</Name></File><File><Name>ep22_2014.wem</Name></File></FilesList></Path><Path><StateList><State><Name>Torpedo_Location</Name><Value>Torpedo_Left</Value></State></StateList><FilesList><File><Name>ep01_1310.wem</Name></File><File><Name>ep06_1035.wem</Name></File><File><Name>ep22_2014.wem</Name></File></FilesList></Path><Path><StateList><State><Name>Torpedo_Location</Name><Value>Torpedo_Right</Value></State></StateList><FilesList><File><Name>ep01_1310.wem</Name></File><File><Name>ep06_1035.wem</Name></File><File><Name>ep22_2014.wem</Name></File></FilesList></Path></Container></ExternalEvent><ExternalEvent><Name>Play_UI_Defective_Modules</Name><Container><Name>Voice</Name><ExternalId>VUI_Defective_Modules</ExternalId><Path><StateList><State><Name>ModuleState</Name><Value>Crit</Value></State><State><Name>ModuleType</Name><Value>Engine</Value></State></StateList><FilesList><File><Name>ep02_0830.wem</Name></File></FilesList></Path><Path><StateList><State><Name>ModuleState</Name><Value>Crit</Value></State><State><Name>ModuleType</Name><Value>MainGun</Value></State></StateList><FilesList><File><Name>ep02_1322.wem</Name></File><File><Name>ep06_1138.wem</Name></File></FilesList></Path><Path><StateList><State><Name>ModuleState</Name><Value>Crit</Value></State><State><Name>ModuleType</Name><Value>StreeringWheel</Value></State></StateList><FilesList><File><Name>ep01_1644.wem</Name></File></FilesList></Path><Path><StateList><State><Name>ModuleState</Name><Value>Dead</Value></State><State><Name>ModuleType</Name><Value>MainGun</Value></State></StateList><FilesList><File><Name>ep02_0912.wem</Name></File></FilesList></Path><Path><StateList><State><Name>ModuleState</Name><Value>Dead</Value></State><State><Name>ModuleType</Name><Value>TorpedoGun</Value></State></StateList><FilesList><File><Name>ep02_0912.wem</Name></File></FilesList></Path></Container></ExternalEvent></AudioModification></AudioModification.xml>